Metadata-Version: 2.1
Name: feriados-municipais
Version: 0.1.5
Summary: Versão beta da biblioteca de feriados municipais.
Author: Luiz Fernando Teles Rodrigues
Author-email: euluizfernando2001@gmail.com
License: MIT License
Keywords: feriados br municipais brasil
License-File: LICENCE
